aiopioneer/__init__.py
aiopioneer/cli.py
aiopioneer/command_queue.py
aiopioneer/connection.py
aiopioneer/const.py
aiopioneer/decode.py
aiopioneer/exceptions.py
aiopioneer/params.py
aiopioneer/pioneer_avr.py
aiopioneer/properties.py
aiopioneer/property_entry.py
aiopioneer/property_registry.py
aiopioneer/util.py
aiopioneer/decoders/__init__.py
aiopioneer/decoders/amp.py
aiopioneer/decoders/audio.py
aiopioneer/decoders/code_map.py
aiopioneer/decoders/dsp.py
aiopioneer/decoders/response.py
aiopioneer/decoders/system.py
aiopioneer/decoders/tuner.py
aiopioneer/decoders/video.py
aiopioneer-0.10.2.dist-info/METADATA
aiopioneer-0.10.2.dist-info/WHEEL
aiopioneer-0.10.2.dist-info/entry_points.txt
aiopioneer-0.10.2.dist-info/licenses/LICENSE
aiopioneer-0.10.2.dist-info/RECORD
