Metadata-Version: 2.4
Name: aiopioneer
Version: 0.10.2
Summary: Asyncio Python library for controlling a Pioneer AVR via its API
Project-URL: Homepage, https://github.com/crowbarz/aiopioneer
Project-URL: Issues, https://github.com/crowbarz/aiopioneer/issues
Author-email: Crowbar Z <crowbarz@outlook.com>
License-File: LICENSE
Classifier: Framework :: AsyncIO
Classifier: Intended Audience :: Developers
Classifier: License :: OSI Approved :: Apache Software License
Classifier: Programming Language :: Python
Classifier: Programming Language :: Python :: 3.11
Classifier: Topic :: Home Automation
Classifier: Topic :: Software Development :: Libraries :: Python Modules
Requires-Python: >=3.11
Requires-Dist: aioconsole~=0.8
Requires-Dist: pyyaml~=6.0
